{
  "$schema": "https://developer.microsoft.com/en-us/json-schemas/teams/v1.5/MicrosoftTeams.schema.json",
  "name.short": "Expert Finder",
  "name.full": "Expert Finder",
  "description.short": "Mit Expert Finder können Benutzer nach Experten basierend auf Attributen suchen",
  "description.full": "Mithilfe von Expert Finder können Benutzer in einer Organisation basierend auf Qualifikationen, Interessen oder besuchten Bildungseinrichtungen nach Experten suchen. Darüber hinaus bietet Expert Finder Benutzern auch die Möglichkeit, Ihre Profilinformationen zu aktualisieren und auf dem neuesten Stand zu halten.",
  "bots[0].commandLists[0].commands[0].title": "Mein Profil",
  "bots[0].commandLists[0].commands[0].description": "Mein Profil",
  "bots[0].commandLists[0].commands[1].title": "Suchen",
  "bots[0].commandLists[0].commands[1].description": "Personen suchen",
  "bots[0].commandLists[0].commands[2].title": "Abmelden",
  "bots[0].commandLists[0].commands[2].description": "Von Expert Finder abmelden",
  "composeExtensions[0].commands[0].title": "Qualifikationen",
  "composeExtensions[0].commands[0].description": "Experten basierend auf Fähigkeiten suchen",
  "composeExtensions[0].commands[0].parameters[0].title": "Qualifikationen",
  "composeExtensions[0].commands[0].parameters[0].description": "Experten basierend auf Fähigkeiten suchen",
  "composeExtensions[0].commands[1].title": "Interessen",
  "composeExtensions[0].commands[1].description": "Experten basierend auf Interessen suchen",
  "composeExtensions[0].commands[1].parameters[0].title": "Interessen",
  "composeExtensions[0].commands[1].parameters[0].description": "Experten basierend auf Interessen suchen",
  "composeExtensions[0].commands[2].title": "Bildungseinrichtungen",
  "composeExtensions[0].commands[2].description": "Experten basierend auf Bildungseinrichtungen suchen",
  "composeExtensions[0].commands[2].parameters[0].title": "Bildungseinrichtungen",
  "composeExtensions[0].commands[2].parameters[0].description": "Experten basierend auf Bildungseinrichtungen suchen"
}